src/register_file.v
//BUSTY BITS
//Calalan, Sherwin
//Chua, Kyle
//Cruz, Miguel
//Tirona, Paul
module register_file(
elk, nrst,
rd_addrA, rd_addrB,
wr_addr, wr_en, wr_data,
rd_dataA, rd_dataB
);

input wire elk, nrst;
input wire [4:0] rd_addrA, rd_addrB;
input wire [4:0] wr_addr;
input wire wr_en;
input wire [31:0] wr_data;
output reg [31:0] rd_dataA, rd_dataB;
reg [31:0] registers [31:0];
integer ctr;

initial begin //Reset at the beginning
	for(ctr=1; ctr<32; ctr++) begin
		registers[ctr] <= 32'd0;
	end

	rd_dataA <= 32'd0;
	rd_dataB <= 32'd0;
end

always @ (rd_addrA) begin //Execute when rd_addrA is changed
	rd_dataA = #1 registers[rd_addrA];
end

always @ (rd_addrB) begin //Execute when rd_addrB is changed
	rd_dataB = #1 registers[rd_addrB];
end

always @ (posedge elk) begin //Execute when clock is postive edge
	if(wr_en == 1'b1) begin //Check if write is enabled
		registers[wr_addr] = #1 wr_data;
	end
end

always @ (posedge nrst) begin //Execute when reset is asserted
	for(ctr=1; ctr<32; ctr++) begin
		registers[ctr] <= 32'd0;
	end

	rd_dataA <= 32'd0;
	rd_dataB <= 32'd0;
end

endmodule

src/register_tb.v
`include "register_file.v"
module register_tb();
	reg elk;
	reg nrst;
	reg[4:0] rd_addrA;
	reg[4:0] rd_addrB;
	reg[4:0] wr_addr; 
	reg wr_en;
	reg[31:0] wr_data;


	reg[31:0] R[31:0];
	integer ctr;
	reg tempA, tempB;
	output wire [31:0] rd_dataA;
	output wire [31:0] rd_dataB;
	
	integer counter;
	
	
initial begin
	$dumpfile("register_file.vcd");
	$dumpvars(0, elk, nrst, rd_addrA, rd_addrB, wr_addr, wr_en, wr_data, rd_dataA, rd_dataB);
	elk =1;
	
	#20
	wr_en = 1;
	wr_addr = 32'd8;
	wr_data = 32'h11111111;
	#6
	rd_addrA = wr_addr;	
	
	#25
	wr_en = 1;
	wr_addr = 32'd9;
	wr_data = 32'h22222222;
	#6
	rd_addrB = wr_addr;
	
	#10
	nrst = 0;
	#5
	nrst = 0;
	rd_addrA = wr_addr;	
	rd_addrB = wr_addr;
	
	#30
	
	$finish;
end


always begin
	
	#5 elk = ~elk; //toggle clock every 5 ticks

end

register_file U_register(elk, nrst, rd_addrA, rd_addrB, wr_addr, wr_en, wr_data, rd_dataA, rd_dataB);

endmodule

src/register_file.vcd
$date
	Sat Jan 28 15:29:11 2017
$end
$version
	Icarus Verilog
$end
$timescale
	1s
$end
$scope module register_tb $end
$var reg 1 ! elk $end
$upscope $end
$scope module register_tb $end
$var reg 1 " nrst $end
$upscope $end
$scope module register_tb $end
$var reg 5 # rd_addrA [4:0] $end
$upscope $end
$scope module register_tb $end
$var reg 5 $ rd_addrB [4:0] $end
$upscope $end
$scope module register_tb $end
$var reg 5 % wr_addr [4:0] $end
$upscope $end
$scope module register_tb $end
$var reg 1 & wr_en $end
$upscope $end
$scope module register_tb $end
$var reg 32 ' wr_data [31:0] $end
$upscope $end
$scope module register_tb $end
$var wire 32 ( rd_dataA [31:0] $end
$upscope $end
$scope module register_tb $end
$var wire 32 ) rd_dataB [31:0] $end
$upscope $end
$enddefinitions $end
#0
$dumpvars
b0 )
b0 (
bx '
x&
bx %
bx $
bx #
x"
1!
$end
#5
0!
#10
1!
#15
0!
#20
1!
b10001000100010001000100010001 '
b1000 %
1&
#21
b1000 #
#22
b10001000100010001000100010001 (
#25
0!
#30
1!
#35
0!
#40
1!
#45
0!
#46
b100010001000100010001000100010 '
b1001 %
#47
b1001 $
#50
1!
#55
0!
#57
0"
#60
1!
#62
b1001 #
#63
b100010001000100010001000100010 (
#65
0!
#70
1!
#75
0!
#80
1!
#85
0!
#90
1!
